{
  "minecraft:recipes/decorations/iron_bars": {
    "criteria": {
      "has_iron_ingot": "2021-04-28 10:33:18 +0200"
    },
    "done": true
  },
  "minecraft:recipes/tools/golden_pickaxe": {
    "criteria": {
      "has_gold_ingot": "2021-04-28 10:33:10 +0200"
    },
    "done": true
  },
  "minecraft:recipes/combat/iron_sword": {
    "criteria": {
      "has_iron_ingot": "2021-04-28 10:33:18 +0200"
    },
    "done": true
  },
  "minecraft:recipes/building_blocks/polished_diorite_stairs_from_diorite_stonecutting": {
    "criteria": {
      "has_diorite": "2021-04-28 11:13:33 +0200"
    },
    "done": true
  },
  "minecraft:recipes/building_blocks/gold_block": {
    "criteria": {
      "has_gold_ingot": "2021-04-28 10:33:10 +0200"
    },
    "done": true
  },
  "minecraft:recipes/combat/golden_chestplate": {
    "criteria": {
      "has_gold_ingot": "2021-04-28 10:33:10 +0200"
    },
    "done": true
  },
  "minecraft:recipes/combat/diamond_chestplate": {
    "criteria": {
      "has_diamond": "2021-04-28 10:13:18 +0200"
    },
    "done": true
  },
  "minecraft:recipes/tools/diamond_axe": {
    "criteria": {
      "has_diamond": "2021-04-28 10:13:18 +0200"
    },
    "done": true
  },
  "minecraft:recipes/tools/iron_pickaxe": {
    "criteria": {
      "has_iron_ingot": "2021-04-28 10:33:18 +0200"
    },
    "done": true
  },
  "minecraft:recipes/transportation/minecart": {
    "criteria": {
      "has_iron_ingot": "2021-04-28 10:33:18 +0200"
    },
    "done": true
  },
  "minecraft:recipes/misc/beacon": {
    "criteria": {
      "has_nether_star": "2021-04-28 10:34:38 +0200"
    },
    "done": true
  },
  "minecraft:adventure/adventuring_time": {
    "criteria": {
      "minecraft:forest": "2021-04-28 10:12:13 +0200",
      "minecraft:river": "2021-04-28 10:13:34 +0200"
    },
    "done": false
  },
  "minecraft:recipes/redstone/iron_door": {
    "criteria": {
      "has_iron_ingot": "2021-04-28 10:33:18 +0200"
    },
    "done": true
  },
  "minecraft:recipes/combat/diamond_leggings": {
    "criteria": {
      "has_diamond": "2021-04-28 10:13:18 +0200"
    },
    "done": true
  },
  "minecraft:recipes/misc/book": {
    "criteria": {
      "has_paper": "2021-04-28 10:12:44 +0200"
    },
    "done": true
  },
  "minecraft:recipes/decorations/campfire": {
    "criteria": {
      "has_coal": "2021-04-28 10:51:25 +0200"
    },
    "done": true
  },
  "minecraft:recipes/tools/golden_hoe": {
    "criteria": {
      "has_gold_ingot": "2021-04-28 10:33:10 +0200"
    },
    "done": true
  },
  "minecraft:recipes/tools/iron_hoe": {
    "criteria": {
      "has_iron_ingot": "2021-04-28 10:33:18 +0200"
    },
    "done": true
  },
  "minecraft:recipes/building_blocks/polished_diorite_slab_from_polished_diorite_stonecutting": {
    "criteria": {
      "has_polished_diorite": "2021-04-28 11:13:33 +0200"
    },
    "done": true
  },
  "minecraft:recipes/misc/iron_nugget": {
    "criteria": {
      "has_iron_ingot": "2021-04-28 10:33:18 +0200"
    },
    "done": true
  },
  "minecraft:recipes/decorations/chest": {
    "criteria": {
      "has_lots_of_items": "2021-04-28 10:32:45 +0200"
    },
    "done": true
  },
  "minecraft:recipes/combat/golden_sword": {
    "criteria": {
      "has_gold_ingot": "2021-04-28 10:33:10 +0200"
    },
    "done": true
  },
  "minecraft:recipes/transportation/birch_boat": {
    "criteria": {
      "in_water": "2021-04-28 11:13:00 +0200"
    },
    "done": true
  },
  "minecraft:recipes/food/golden_apple": {
    "criteria": {
      "has_gold_ingot": "2021-04-28 10:33:10 +0200"
    },
    "done": true
  },
  "minecraft:recipes/building_blocks/iron_block": {
    "criteria": {
      "has_iron_ingot": "2021-04-28 10:33:18 +0200"
    },
    "done": true
  },
  "minecraft:recipes/building_blocks/polished_diorite_slab": {
    "criteria": {
      "has_polished_diorite": "2021-04-28 11:13:33 +0200"
    },
    "done": true
  },
  "minecraft:recipes/tools/iron_shovel": {
    "criteria": {
      "has_iron_ingot": "2021-04-28 10:33:18 +0200"
    },
    "done": true
  },
  "minecraft:recipes/transportation/acacia_boat": {
    "criteria": {
      "in_water": "2021-04-28 11:13:00 +0200"
    },
    "done": true
  },
  "minecraft:recipes/combat/diamond_sword": {
    "criteria": {
      "has_diamond": "2021-04-28 10:13:18 +0200"
    },
    "done": true
  },
  "minecraft:recipes/redstone/iron_trapdoor": {
    "criteria": {
      "has_iron_ingot": "2021-04-28 10:33:18 +0200"
    },
    "done": true
  },
  "minecraft:recipes/decorations/smithing_table": {
    "criteria": {
      "has_iron_ingot": "2021-04-28 10:33:18 +0200"
    },
    "done": true
  },
  "minecraft:recipes/tools/shears": {
    "criteria": {
      "has_iron_ingot": "2021-04-28 10:33:18 +0200"
    },
    "done": true
  },
  "minecraft:recipes/building_blocks/coal_block": {
    "criteria": {
      "has_coal": "2021-04-28 10:51:25 +0200"
    },
    "done": true
  },
  "minecraft:recipes/transportation/jungle_boat": {
    "criteria": {
      "in_water": "2021-04-28 11:13:00 +0200"
    },
    "done": true
  },
  "minecraft:recipes/decorations/jukebox": {
    "criteria": {
      "has_diamond": "2021-04-28 10:13:18 +0200"
    },
    "done": true
  },
  "minecraft:recipes/redstone/light_weighted_pressure_plate": {
    "criteria": {
      "has_gold_ingot": "2021-04-28 10:33:10 +0200"
    },
    "done": true
  },
  "minecraft:recipes/transportation/spruce_boat": {
    "criteria": {
      "in_water": "2021-04-28 11:13:00 +0200"
    },
    "done": true
  },
  "minecraft:recipes/building_blocks/diamond_block": {
    "criteria": {
      "has_diamond": "2021-04-28 10:13:18 +0200"
    },
    "done": true
  },
  "minecraft:recipes/redstone/heavy_weighted_pressure_plate": {
    "criteria": {
      "has_iron_ingot": "2021-04-28 10:33:18 +0200"
    },
    "done": true
  },
  "minecraft:recipes/transportation/dark_oak_boat": {
    "criteria": {
      "in_water": "2021-04-28 11:13:00 +0200"
    },
    "done": true
  },
  "minecraft:recipes/tools/diamond_pickaxe": {
    "criteria": {
      "has_diamond": "2021-04-28 10:13:18 +0200"
    },
    "done": true
  },
  "minecraft:recipes/tools/diamond_hoe": {
    "criteria": {
      "has_diamond": "2021-04-28 10:13:18 +0200"
    },
    "done": true
  },
  "minecraft:recipes/misc/conduit": {
    "criteria": {
      "has_nautilus_core": "2021-04-28 10:33:23 +0200"
    },
    "done": true
  },
  "minecraft:recipes/building_blocks/emerald_block": {
    "criteria": {
      "has_emerald": "2021-04-28 10:33:51 +0200"
    },
    "done": true
  },
  "minecraft:recipes/tools/diamond_shovel": {
    "criteria": {
      "has_diamond": "2021-04-28 10:13:18 +0200"
    },
    "done": true
  },
  "minecraft:recipes/misc/gold_nugget": {
    "criteria": {
      "has_gold_ingot": "2021-04-28 10:33:10 +0200"
    },
    "done": true
  },
  "minecraft:recipes/combat/iron_leggings": {
    "criteria": {
      "has_iron_ingot": "2021-04-28 10:33:18 +0200"
    },
    "done": true
  },
  "minecraft:recipes/tools/golden_axe": {
    "criteria": {
      "has_gold_ingot": "2021-04-28 10:33:10 +0200"
    },
    "done": true
  },
  "minecraft:recipes/tools/iron_axe": {
    "criteria": {
      "has_iron_ingot": "2021-04-28 10:33:18 +0200"
    },
    "done": true
  },
  "minecraft:recipes/combat/golden_leggings": {
    "criteria": {
      "has_gold_ingot": "2021-04-28 10:33:10 +0200"
    },
    "done": true
  },
  "minecraft:recipes/combat/shield": {
    "criteria": {
      "has_iron_ingot": "2021-04-28 10:33:18 +0200"
    },
    "done": true
  },
  "minecraft:recipes/building_blocks/sea_lantern": {
    "criteria": {
      "has_prismarine_crystals": "2021-04-28 10:34:24 +0200"
    },
    "done": true
  },
  "minecraft:recipes/combat/golden_helmet": {
    "criteria": {
      "has_gold_ingot": "2021-04-28 10:33:10 +0200"
    },
    "done": true
  },
  "minecraft:recipes/decorations/lantern": {
    "criteria": {
      "has_iron_ingot": "2021-04-28 10:33:18 +0200"
    },
    "done": true
  },
  "minecraft:recipes/misc/bucket": {
    "criteria": {
      "has_iron_ingot": "2021-04-28 10:33:18 +0200"
    },
    "done": true
  },
  "minecraft:recipes/combat/iron_boots": {
    "criteria": {
      "has_iron_ingot": "2021-04-28 10:33:18 +0200"
    },
    "done": true
  },
  "minecraft:recipes/redstone/hopper": {
    "criteria": {
      "has_iron_ingot": "2021-04-28 10:33:18 +0200"
    },
    "done": true
  },
  "minecraft:recipes/building_blocks/polished_diorite_stairs_from_polished_diorite_stonecutting": {
    "criteria": {
      "has_polished_diorite": "2021-04-28 11:13:33 +0200"
    },
    "done": true
  },
  "minecraft:recipes/decorations/chain": {
    "criteria": {
      "has_iron_ingot": "2021-04-28 10:33:18 +0200"
    },
    "done": true
  },
  "minecraft:recipes/decorations/cartography_table": {
    "criteria": {
      "has_paper": "2021-04-28 10:12:44 +0200"
    },
    "done": true
  },
  "minecraft:recipes/building_blocks/polished_diorite_stairs": {
    "criteria": {
      "has_polished_diorite": "2021-04-28 11:13:33 +0200"
    },
    "done": true
  },
  "minecraft:recipes/combat/diamond_boots": {
    "criteria": {
      "has_diamond": "2021-04-28 10:13:18 +0200"
    },
    "done": true
  },
  "minecraft:story/mine_diamond": {
    "criteria": {
      "diamond": "2021-04-28 10:13:18 +0200"
    },
    "done": true
  },
  "minecraft:recipes/combat/diamond_helmet": {
    "criteria": {
      "has_diamond": "2021-04-28 10:13:18 +0200"
    },
    "done": true
  },
  "minecraft:story/root": {
    "criteria": {
      "crafting_table": "2021-04-28 10:13:24 +0200"
    },
    "done": true
  },
  "minecraft:recipes/combat/iron_chestplate": {
    "criteria": {
      "has_iron_ingot": "2021-04-28 10:33:18 +0200"
    },
    "done": true
  },
  "minecraft:recipes/combat/crossbow": {
    "criteria": {
      "has_iron_ingot": "2021-04-28 10:33:18 +0200"
    },
    "done": true
  },
  "minecraft:recipes/transportation/oak_boat": {
    "criteria": {
      "in_water": "2021-04-28 11:13:00 +0200"
    },
    "done": true
  },
  "minecraft:story/smelt_iron": {
    "criteria": {
      "iron": "2021-04-28 10:33:18 +0200"
    },
    "done": true
  },
  "minecraft:recipes/building_blocks/polished_diorite_slab_from_diorite_stonecutting": {
    "criteria": {
      "has_diorite": "2021-04-28 11:13:33 +0200"
    },
    "done": true
  },
  "minecraft:recipes/tools/golden_shovel": {
    "criteria": {
      "has_gold_ingot": "2021-04-28 10:33:10 +0200"
    },
    "done": true
  },
  "minecraft:recipes/combat/golden_boots": {
    "criteria": {
      "has_gold_ingot": "2021-04-28 10:33:10 +0200"
    },
    "done": true
  },
  "minecraft:recipes/combat/iron_helmet": {
    "criteria": {
      "has_iron_ingot": "2021-04-28 10:33:18 +0200"
    },
    "done": true
  },
  "DataVersion": 2586
}